AUTHORS
CHANGELOG.txt
DESCRIPTION
LICENSE
MANIFEST.in
README.rst
setup.cfg
setup.py
tox.ini
django_freckle_budgets.egg-info/PKG-INFO
django_freckle_budgets.egg-info/SOURCES.txt
django_freckle_budgets.egg-info/dependency_links.txt
django_freckle_budgets.egg-info/requires.txt
django_freckle_budgets.egg-info/top_level.txt
freckle_budgets/__init__.py
freckle_budgets/admin.py
freckle_budgets/freckle_api.py
freckle_budgets/models.py
freckle_budgets/urls.py
freckle_budgets/utils.py
freckle_budgets/views.py
freckle_budgets/migrations/0001_initial.py
freckle_budgets/migrations/0002_employee.py
freckle_budgets/migrations/0003_employeeprojectmonth.py
freckle_budgets/migrations/0004_projectmonth_overhead_previous_month.py
freckle_budgets/migrations/0005_freetime.py
freckle_budgets/migrations/__init__.py
freckle_budgets/south_migrations/0001_initial.py
freckle_budgets/south_migrations/0002_auto__add_employee.py
freckle_budgets/south_migrations/0003_auto__add_employeeprojectmonth.py
freckle_budgets/south_migrations/0004_auto__add_field_projectmonth_overhead_previous_month.py
freckle_budgets/south_migrations/0005_auto__add_freetime.py
freckle_budgets/south_migrations/__init__.py
freckle_budgets/static/.empty
freckle_budgets/static/freckle_budgets/.empty
freckle_budgets/static/freckle_budgets/css/styles.css
freckle_budgets/templates/freckle_budgets/.empty
freckle_budgets/templates/freckle_budgets/year_view.html
freckle_budgets/templatetags/__init__.py
freckle_budgets/templatetags/freckle_budgets_tags.py
freckle_budgets/tests/.coverage
freckle_budgets/tests/.coveragerc
freckle_budgets/tests/__init__.py
freckle_budgets/tests/factories.py
freckle_budgets/tests/fixtures.py
freckle_budgets/tests/freckle_api_tests.py
freckle_budgets/tests/freckle_budget_tags_tests.py
freckle_budgets/tests/local_settings.py.sample
freckle_budgets/tests/models_tests.py
freckle_budgets/tests/runtests.py
freckle_budgets/tests/south_settings.py
freckle_budgets/tests/test_settings.py
freckle_budgets/tests/urls.py
freckle_budgets/tests/utils_tests.py
freckle_budgets/tests/views_tests.py
freckle_budgets/tests/test_app/__init__.py
freckle_budgets/tests/test_app/models.py
freckle_budgets/tests/test_app/templates/400.html
