Metadata-Version: 1.0
Name: django-freckle-budgets
Version: 0.2
Summary: A reusable Django app that allows to plan year budgets and track them via letsfreckle.
